geonevados/__init__.py
geonevados/common.py
geonevados/geonevados.py
geonevados-0.0.2.dist-info/LICENSE
geonevados-0.0.2.dist-info/METADATA
geonevados-0.0.2.dist-info/WHEEL
geonevados-0.0.2.dist-info/top_level.txt
geonevados-0.0.2.dist-info/RECORD
